setup.py
src/Backend/__init__.py
src/Backend/command_list.py
src/Backend/command_parser.py
src/Backend/interaction_manager.py
src/Backend/user_input.py
src/Backend/State/__init__.py
src/Backend/State/instance.py
src/Backend/State/SyntaxTokens/__init__.py
src/Backend/State/SyntaxTokens/color_config.py
src/Backend/State/SyntaxTokens/syntax_parser.py
src/Backend/State/SyntaxTokens/syntax_test.py
src/Backend/interaction_managers/__init__.py
src/Backend/interaction_managers/cursor_logic.py
src/Backend/interaction_managers/graphics_logic.py
src/Backend/interaction_managers/text_logic.py
src/Frontend/__init__.py
src/Frontend/color_config.py
src/Frontend/text_canvas.py
src/plugins/__init__.py
src/plugins/fuzzy_file_select_meta.py
src/shim.egg-info/PKG-INFO
src/shim.egg-info/SOURCES.txt
src/shim.egg-info/dependency_links.txt
src/shim.egg-info/entry_points.txt
src/shim.egg-info/requires.txt
src/shim.egg-info/top_level.txt