Metadata-Version: 1.1
Name: shim
Version: 0.1.0
Summary: Vim for Python
Home-page: https://github.com/swong15/shim
Author:  
Author-email:  
License: UNKNOWN
Keywords: shim vim emacs
Platform: UNKNOWN
Classifier: Development Status :: 3 - Alpha
Classifier: Environment :: Console
Classifier: Intended Audience :: Developers
Classifier: Natural Language :: English
Classifier: Programming Language :: Python :: 2.7
Classifier: License :: Other/Proprietary License
